jaso_jamo/JasoJamoDecoder.py
jaso_jamo/JasoJamoTokenizer.py
jaso_jamo/__init__.py
jaso_jamo/core.py
jaso_jamo-1.0.2.dist-info/licenses/LICENSE
jaso_jamo-1.0.2.dist-info/METADATA
jaso_jamo-1.0.2.dist-info/WHEEL
jaso_jamo-1.0.2.dist-info/top_level.txt
jaso_jamo-1.0.2.dist-info/RECORD
