Metadata-Version: 2.4
Name: jaso-jamo
Version: 1.0.2
Summary: 한글 자소 분리 및 복원 라이브러리 (5단계 Fallback 방식)
Author-email: c0z0c <c0z0c.dev@gmail.com>
License-Expression: MIT
Project-URL: Homepage, https://github.com/c0z0c/jaso-jamo
Project-URL: Repository, https://github.com/c0z0c/jaso-jamo
Project-URL: Issues, https://github.com/c0z0c/jaso-jamo/issues
Project-URL: Documentation, https://github.com/c0z0c/jaso-jamo#readme
Keywords: hangul,korean,jamo,jaso,tokenizer,nlp,자소,한글
Classifier: Development Status :: 4 - Beta
Classifier: Intended Audience :: Developers
Classifier: Intended Audience :: Science/Research
Classifier: Programming Language :: Python :: 3
Classifier: Programming Language :: Python :: 3.7
Classifier: Programming Language :: Python :: 3.8
Classifier: Programming Language :: Python :: 3.9
Classifier: Programming Language :: Python :: 3.10
Classifier: Programming Language :: Python :: 3.11
Classifier: Programming Language :: Python :: 3.12
Classifier: Topic :: Text Processing :: Linguistic
Classifier: Topic :: Software Development :: Libraries :: Python Modules
Classifier: Natural Language :: Korean
Requires-Python: >=3.7
License-File: LICENSE
Provides-Extra: dev
Requires-Dist: pytest>=7.0.0; extra == "dev"
Requires-Dist: pytest-cov>=4.0.0; extra == "dev"
Requires-Dist: black>=23.0.0; extra == "dev"
Requires-Dist: isort>=5.0.0; extra == "dev"
Dynamic: license-file
